aka_data_prep
