Metadata-Version: 2.1
Name: aka-data-prep
Version: 0.1.2
Summary: Tools for data preparation, cleaning, and preprocessing
Author: Kader Geraldo
